README.md
geo_subsampler/__init__.py
geo_subsampler/phylogenetic_diversity.py
geo_subsampler-0.2.dist-info/LICENSE
geo_subsampler-0.2.dist-info/METADATA
geo_subsampler-0.2.dist-info/WHEEL
geo_subsampler-0.2.dist-info/entry_points.txt
geo_subsampler-0.2.dist-info/top_level.txt
geo_subsampler-0.2.dist-info/RECORD
