Metadata-Version: 2.1
Name: geo_subsampler
Version: 0.2
Summary: Subsampling of rooted phylogenetic trees using phylogenetic diversity and location proportions.
Home-page: https://github.com/evolbioinfo/geo_subsampler
Author: Anna Zhukova
Author-email: anna.zhukova@pasteur.fr
Keywords: phylogenetics,subsampling,phylogenetic diversity,phylogeography
Classifier: Development Status :: 4 - Beta
Classifier: Environment :: Console
Classifier: Intended Audience :: Developers
Classifier: Topic :: Scientific/Engineering :: Bio-Informatics
Classifier: Topic :: Software Development
Classifier: Topic :: Software Development :: Libraries :: Python Modules
Classifier: Programming Language :: Python :: 3
Classifier: Programming Language :: Python :: 3 :: Only
Requires: pandas
Requires: numpy
Requires: ete3
License-File: LICENSE
Requires-Dist: pandas
Requires-Dist: numpy
Requires-Dist: ete3
